{
    "lines": [
        {
            "delays": [
                240,
                300
            ],
            "name": "Metro",
            "scheme": null,
            "segments": [
                [
                    0,
                    1,
                    0
                ],
                [
                    1,
                    0,
                    0
                ],
                [
                    1,
                    2,
                    0
                ],
                [
                    2,
                    1,
                    0
                ],
                [
                    2,
                    3,
                    0
                ],
                [
                    3,
                    2,
                    0
                ],
                [
                    3,
                    4,
                    0
                ],
                [
                    4,
                    3,
                    0
                ],
                [
                    4,
                    5,
                    0
                ],
                [
                    5,
                    4,
                    0
                ],
                [
                    5,
                    6,
                    0
                ],
                [
                    6,
                    5,
                    0
                ],
                [
                    6,
                    7,
                    0
                ],
                [
                    7,
                    6,
                    0
                ],
                [
                    7,
                    8,
                    60
                ],
                [
                    8,
                    7,
                    60
                ],
                [
                    8,
                    9,
                    60
                ],
                [
                    9,
                    8,
                    60
                ],
                [
                    9,
                    10,
                    60
                ],
                [
                    10,
                    9,
                    60
                ],
                [
                    10,
                    11,
                    120
                ],
                [
                    11,
                    10,
                    120
                ],
                [
                    11,
                    12,
                    120
                ],
                [
                    12,
                    11,
                    120
                ],
                [
                    12,
                    13,
                    120
                ],
                [
                    13,
                    12,
                    120
                ],
                [
                    13,
                    14,
                    120
                ],
                [
                    14,
                    13,
                    120
                ],
                [
                    14,
                    15,
                    120
                ],
                [
                    15,
                    14,
                    120
                ],
                [
                    15,
                    16,
                    120
                ],
                [
                    16,
                    15,
                    120
                ],
                [
                    16,
                    17,
                    120
                ],
                [
                    17,
                    16,
                    120
                ],
                [
                    17,
                    18,
                    60
                ],
                [
                    17,
                    21,
                    120
                ],
                [
                    18,
                    17,
                    60
                ],
                [
                    18,
                    19,
                    120
                ],
                [
                    19,
                    18,
                    120
                ],
                [
                    19,
                    20,
                    120
                ],
                [
                    20,
                    19,
                    120
                ],
                [
                    21,
                    17,
                    120
                ],
                [
                    21,
                    22,
                    120
                ],
                [
                    22,
                    21,
                    120
                ],
                [
                    22,
                    23,
                    120
                ],
                [
                    23,
                    22,
                    120
                ]
            ],
            "stations": [
                [
                    0,
                    "Matinkyla",
                    0
                ],
                [
                    1,
                    "Niittymaa",
                    1
                ],
                [
                    2,
                    "Tapiola",
                    2
                ],
                [
                    3,
                    "Otaniemi",
                    3
                ],
                [
                    4,
                    "Keilaniemi",
                    4
                ],
                [
                    5,
                    "Koivusaari",
                    5
                ],
                [
                    6,
                    "Lauttasaari",
                    6
                ],
                [
                    7,
                    "Ruoholahti",
                    7
                ],
                [
                    8,
                    "Kamppi",
                    8
                ],
                [
                    9,
                    "Rautatientori",
                    9
                ],
                [
                    10,
                    "Kaisaniemi",
                    10
                ],
                [
                    11,
                    "Hakaniemi",
                    11
                ],
                [
                    12,
                    "Sornainen",
                    12
                ],
                [
                    13,
                    "Kalasatama",
                    13
                ],
                [
                    14,
                    "Kulosaari",
                    14
                ],
                [
                    15,
                    "Herttoniemi",
                    15
                ],
                [
                    16,
                    "Siilitie",
                    16
                ],
                [
                    17,
                    "Itakeskus",
                    17
                ],
                [
                    18,
                    "Puotila",
                    18
                ],
                [
                    19,
                    "Rastila",
                    19
                ],
                [
                    20,
                    "Vuosaari",
                    20
                ],
                [
                    21,
                    "Myllypuro",
                    21
                ],
                [
                    22,
                    "Kontula",
                    22
                ],
                [
                    23,
                    "Mellunmaki",
                    23
                ]
            ],
            "text_id": 24
        }
    ],
    "name": "metro",
    "transfers": [],
    "type_name": "Метро"
}